nest/__init__.py
nest/common/__init__.py
nest/common/decorators/core/controller.py
nest/common/decorators/core/injectable.py
nest/common/decorators/core/module.py
nest/common/decorators/core/version.py
nest/common/decorators/http/http_code.py
nest/common/decorators/http/request_mapping.py
nest/common/enums/__init__.py
nest/common/enums/version_type.py
nest/common/interfaces/__init__.py
nest/common/interfaces/version_options.py
nest/core/__init__.py
nest/core/application.py
nest/core/container.py
nest/core/nest_factory.py
nestpy_framework-0.2.0.dist-info/LICENSE
nestpy_framework-0.2.0.dist-info/METADATA
nestpy_framework-0.2.0.dist-info/WHEEL
nestpy_framework-0.2.0.dist-info/RECORD
