Metadata-Version: 2.1
Name: nestpy-framework
Version: 0.2.0
Summary: A Python backend framework inspired by NestJS
Author: Manuel S. Lemos
Author-email: manuels.lemos@gmail.com
Requires-Python: >=3.9,<4.0
Classifier: Programming Language :: Python :: 3
Classifier: Programming Language :: Python :: 3.9
Classifier: Programming Language :: Python :: 3.10
Classifier: Programming Language :: Python :: 3.11
Classifier: Programming Language :: Python :: 3.12
Classifier: Programming Language :: Python :: 3.13
Requires-Dist: fastapi (==0.104.0)
Requires-Dist: pydantic (==2.4.2)
Requires-Dist: uvicorn (==0.24.0)
